Workbook

Sheet Triage
A1: Decision | B1: Notes | C1: Questions | D1: Court | E1: Citation | F1: Case name | G1: Date | H1: Max hits | I1: Citing count | J1: Found by search | K1: Snippet
C2: Q1 | D2: SCC | E2: 2026 SCC 5 | F2: Taylor v. Newfoundland and Labrador | G2: 2026-02-13 | H2: 6 | I2: 13 | J2: q1_justiciability | K2: en, and Leena Grover. “General Comments of the Human Rights Committee and their legitimacy”, in Helen Keller and Geir Ulfstein, eds., assisted by Leena Grover, UN Human Rights Treaty Bodies: Law and Legitimacy, Cambridge: Cambridge University Press, 2012, 116. Kennedy, Gerard J., and Lorne Sossin. “Justiciability, Access to Justice and the Development of Constitutional Law in Canada” (2017), 45 Fed. L. Rev. 707. Labelle Eastaugh, Érik. “The Precautionary Principle as a Justification for Limiting Constitutional Rights” (2025), 62 Alta. L. Rev. 818. Laskin, John B. “Mobility Rights under the Cha ... rd University Press, 2015. Schmeiser, Douglas A., and Katherine J. Young. “Mobility Rights in Canada” (1983), 13 Man. L.J. 615. Sharpe, Robert J., and Kent Roach. The Charter of Rights and Freedoms, 7th ed. Toronto: Irwin Law, 2021. Sossin, Lorne. “The Unfinished Project of Roncarelli v. Duplessis: Justiciability, Discretion and the Limits of the Rule of Law” (2010), 55 McGill L.J. 661. Sossin, Lorne M., and Gerard Kennedy. Boundaries of Judicial Review: The Law of Justiciability in Canada, 3rd ed. Toronto: Thomson Reuters, 2024. Strayer, Barry L. Canada’s Constitutional Revolution. Edmonton:
C3: Q5 | D3: SCC | E3: 2025 SCC 38 | F3: Dorsey v. Canada (Attorney General) | G3: 2025-11-21 | H3: 3 | I3: 7 | J3: q5_scc | K3: l 160 days after the impugned decision (Federal Courts Act, R.S.C. 1985, c. F-7, s. 18.1(2); Federal Courts Rules, SOR/98-106, rr. 301 to 314); (2) the remedy following a successful judicial review in Federal Court will generally be an order for redetermination, not release — there is no history of mandamus being used by the Federal Court to release a detainee (see Chhina, at para. 65); (3) the scope of review in habeas corpus is broader as it reviews the legality of the detention as a whole, rather than one particular administrative decision (see para. 64); (4) judicial review is discretionar ... a, at para. 47). [84] The respondent also argues that provincial superior courts lack the remedial jurisdiction to order that inmates be placed in a lower security institution where they have never previously been housed. This is because provincial superior courts lack jurisdiction over certiorari, mandamus, or declaratory relief in relation to federal administrative bodies (R.F., at paras. 80-83). [85] This argument adopts a very narrow understanding of habeas corpus relief that is contrary to this Court’s jurisprudence. [86] First, while a provincial superior court does not have an inherent
C4: Q5 | D4: SCC | E4: 2024 SCC 35 | F4: R. v. Archambault | G4: 2024-11-01 | H4: 1 | I4: 6 | J4: q5_scc | K4: ies were of a purely procedural nature, as they could always be set aside should the prosecution decide to move forward by way of a direct indictment. B. Superior Court of Quebec [168] Mr. Grenier and Mr. Archambault each challenged these decisions, applying to the Superior Court for certiorari and mandamus on two grounds. They argued first they had the right to a preliminary inquiry because the new rule in s. 535 did not apply to them. They said it would violate the presumption against retrospective application of legislation. Second, even if the new rule applied to them, they argued they nev
C5: Q4 | D5: SCC | E5: 2024 SCC 27 | F5: Ontario (Attorney General) v. Restoule | G5: 2024-07-26 | H5: 1 | I5: 24 | J5: q4_scc | K5: l), [1997] 3 S.C.R. 624, at para. 96; Ardoch Algonquin First Nation v. Canada (Attorney General), 2003 FCA 473, [2004] 2 F.C.R. 108, at paras. 46-47, per Rothstein J.A. (as he then was)). While not a perfect analogy, a direction to this effect bears a family resemblance to an order in the nature of mandamus, insofar as it orders that discretion be exercised, without specifying exactly how (see D. J. M. Brown, J. M. Evans and A. J. Beatty, with the assistance of D. Fairlie, Judicial Review of Administrative Action in Canada (loose-leaf), at § 1:24; British Columbia (Attorney General) v. Canada
C6: Q1 | D6: SCC | E6: 2024 SCC 26 | F6: Canada (Attorney General) v. Power | G6: 2024-07-19 | H6: 40 | I6: 24 | J6: q1_justiciability | K6: ified to eliminate bad faith and abuse of power in enacting primary legislation as grounds for damages under s. 24(1) of the Charter, as they inevitably trench on established categories of parliamentary privilege. They would also strain the separation of powers by asking the courts to entertain non‑justiciable questions. The Crown may, however, be liable in damages under s. 24(1) for harms flowing from “clearly unconstitutional” enactments. The clearly unconstitutional threshold is a nuanced standard that appropriately protects the autonomy of Parliament and the limited immunity necessary for ... ckin. None of the authorities cited in Mackin support awarding Charter damages against the Crown for harms caused by unconstitutional primary legislation. The test enunciated in Mackin also conflicts with the doctrine of parliamentary privilege, as well as the separation of powers and principles of justiciability. None of these points was argued in Mackin, and the Court did not consider them in its reasons. The bad faith and abuse of power thresholds in Mackin are inappropriate thresholds in respect of damages under s. 24(1) of the Charter for unconstitutional primary legislation because they
C7: Q5 | D7: SCC | E7: 2024 SCC 23 | F7: Dow Chemical Canada ULC v. Canada | G7: 2024-06-28 | H7: 6 | I7: 20 | J7: q5_scc | K7: ke her decision under s. 247(10) before or after an assessment is issued. In addition, the Minister might decide not to exercise her discretion under s. 247(10) at all. If the Minister refuses to exercise her discretion, “there is virtually no recourse for the taxpayer, short of obtaining a writ of mandamus” in the Federal Court (p. 326). [53] It cannot be said that the Minister must exercise discretion under s. 247(10) in order for tax liability to be calculated correctly under the ITA. The general non-discretionary rule, which the Crown accurately characterizes as the “default position”, is ... ng a decision by the Minister under s. 247(10) necessarily varies the decision itself, which is part of the process of determining a taxpayer’s liability. A decision by the Tax Court to vary the assessment would therefore require it to quash the Minister’s decision or make an order in the nature of mandamus — powers that are granted only to the Federal Court under ss. 18.1(3) and 18(1)(a), respectively, of the Federal Courts Act. [148] Pursuant to ss. 169 and 171 of the ITA, the Tax Court’s statutory powers on appeal relate to the assessment, which is a product of the process; that product is
C8: Q5 | D8: SCC | E8: 2024 SCC 24 | F8: Iris Technologies Inc. v. Canada | G8: 2024-06-28 | H8: 1 | I8: 29 | J8: q5_scc | K8: 9, to February 29, 2020. The Minister once again withheld the tax refunds. Iris requested on two occasions that the associated funds be released to allow it to maintain and uphold its business operations, but the Minister denied both requests. Following the Minister’s denials, Iris sought a writ of mandamus to compel the release of the funds and filed a motion for interim relief. [70] On April 9, 2020, prior to the hearing of the motion for interim relief, the Minister reassessed Iris for the January to August 2019 reporting periods and assessed it for the September to December 2019 reporting
C9: Q5 | D9: SCC | E9: 2022 SCC 29 | F9: Law Society of Saskatchewan v. Abrametz | G9: 2022-07-08 | H9: 5 | I9: 135 | J9: q5_scc | K9: dering whether an affected party has sought to move matters forward, one has to be mindful of practical impediments to doing so: see, for example, Wachtler, at para. 44. There may be exceptional cases where the affected party may ask the courts to step in, in accordance with the existing rules. (b) Mandamus [80] Mandamus can be sought to compel administrative decision makers to carry out their duties and, in so doing, to limit delay in administrative proceedings: Blencoe, at para. 150. A party who believes he or she is facing undue delay can seek such a remedy, or an order for an expedited hea ... an affected party has sought to move matters forward, one has to be mindful of practical impediments to doing so: see, for example, Wachtler, at para. 44. There may be exceptional cases where the affected party may ask the courts to step in, in accordance with the existing rules. (b) Mandamus [80] Mandamus can be sought to compel administrative decision makers to carry out their duties and, in so doing, to limit delay in administrative proceedings: Blencoe, at para. 150. A party who believes he or she is facing undue delay can seek such a remedy, or an order for an expedited hearing, even bef
C10: Q1 | D10: SCC | E10: 2022 SCC 27 | F10: British Columbia (Attorney General) v. Council of Canadians with Disabilities | G10: 2022-06-23 | H10: 36 | I10: 34 | J10: q1_justiciability | K10: ly, public interest standing should be granted to the organization. The decision to grant or deny public interest standing is discretionary. The Downtown Eastside framework mandates that in exercising its discretion, a court must assess and weigh three factors: (i) whether the case raises a serious justiciable issue; (ii) whether the party bringing the action has a genuine interest in the matter; and (iii) whether the proposed suit is a reasonable and effective means of bringing the case to court. Under this framework, courts flexibly and purposively weigh the factors in light of the particula ... case. Applying the Downtown Eastside framework to the facts in the instant case, the organization raises a serious issue: the constitutionality of laws that implicate the Charter rights of people with mental disabilities. Though the organization’s case is still at the pleadings stage, the issue is justiciable. Material facts are pleaded which, if proven, could support a constitutional claim. The organization has a genuine interest in the issues, and in the challenges faced by people with mental disabilities. The claim is also a reasonable and effective means of bringing the matter before the
C11: Q1 | D11: SCC | E11: 2021 SCC 22 | F11: Ethiopian Orthodox Tewahedo Church of Canada St. Mary Cathedral v. Aga | G11: 2021-05-21 | H11: 6 | I11: 50 | J11: q1_justiciability | K11: n objective intention to enter into legal relations is missing. As such, there is no contract, no jurisdiction and no genuine issue requiring a trial. Courts have jurisdiction to intervene in decisions of voluntary associations only where a legal right is affected. Purely theological issues are not justiciable, but where a legal right is at issue, courts may consider questions that have a religious aspect in vindicating the legal right. Legal rights which can ground jurisdiction include private rights in property, contract, tort or unjust enrichment and statutory causes of action. Natural just ... on form, the form does not mention being bound to the Bylaw. B. Court of Appeal for Ontario, 2020 ONCA 10, 150 O.R. (3d) 516 [16] On appeal, the respondents argued that the Constitution and the Bylaw governing disciplinary measures are contractually binding and enforceable, and there is therefore a justiciable issue to be tried. The Court of Appeal noted that the jurisdiction of a court to address a voluntary association’s own procedures requires an underlying legal right to be adjudicated, such as a contractual right. The Court of Appeal then stated that “[v]oluntary associations do not alway
C12: Q1; Q4; Q5 | D12: SCC | E12: 2020 SCC 5 | F12: Nevsun Resources Ltd. v. Araya | G12: 2020-02-28 | H12: 48 | I12: 186 | J12: q1_justiciability; q4_scc; q5_scc | K12: act of state doctrine. The workers’ claims here are not amenable to adjudication within Canada’s domestic legal order. Instead, they are allocated to the plane of international affairs for resolution in accordance with the principles of public international law and diplomacy. They are therefore not justiciable and should be dismissed in their entirety. There is agreement with the majority that Canada’s choice of law jurisprudence plays a similar role to that of certain aspects of the act of state doctrine; however, the act of state doctrine includes a second branch distinct from choice of law ... issed in their entirety. There is agreement with the majority that Canada’s choice of law jurisprudence plays a similar role to that of certain aspects of the act of state doctrine; however, the act of state doctrine includes a second branch distinct from choice of law which renders some claims non-justiciable. This second branch of the doctrine bars the adjudication of civil actions which have their foundation in allegations that a foreign state has violated public international law. Whether referred to as a branch of the act of state doctrine or as a specific application of the more general
C13: Q5 | D13: SCC | E13: 2019 SCC 65 | F13: Canada (Minister of Citizenship and Immigration) v. Vavilov | G13: 2019-12-19 | H13: 1 | I13: 8231 | J13: q5_scc | K13: dian citizenship before he would be issued a passport. Mr. Vavilov applied for that certificate in October 2012, and it was issued to him on January 15, 2013. At that point, he made another passport application through the Canadian Embassy in Buenos Aires, Argentina, and, after a delay, applied for mandamus, a process that was settled out of court in June 2013. The Minister of Citizenship and Immigration undertook to issue a new travel document to Mr. Vavilov by July 19, 2013. [151] However, Mr. Vavilov never received a passport. Instead, he received a “procedural fairness letter” from the Can
... C491: Q2; Q4 | D491: BCSC | E491: 2007 BCSC 1758 | F491: Lord v. Coulter | G491: 2007-12-05 | H491: 3 | I491: 13 | J491: q2; q4_other | K491: an application for habeas corpus. [63] Similarly, if the matters of sentence management and programming for a particular inmate could be shown to be justiciable, and to be contrary to the duty to act fairly or the Canadian Charter of Rights and Freedoms, to my mind they relate to the remedies of certiorari and mandamus in relation to the CSC and its running of federal institutions. Thus, such matters would fall squarely within the jurisdiction of the Federal

Sheet Summary
A1: How to use
A2: 1. On the Triage sheet, read each Snippet and set Decision (yellow column) to Relevant, Maybe or No. Use Notes for the proposition the case supports.
A3: 2. Filter the Questions column (e.g. 'contains Q2') to work one research question at a time.
A4: 3. Click a Citation to open the full decision.
A5: 4. The table below updates automatically as you mark decisions.
A6: Max hits = most co-occurrence hits in any one search; a high number means sustained discussion, NOT importance. Citing count = times cited by other decisions in the A2AJ corpus searched.
A9: Question | B9: Candidates | C9: Relevant | D9: Maybe | E9: No | F9: Not yet reviewed
A10: Q1 | B10: =COUNTIF(Triage!$C$2:$C$491,"*Q1*") | C10: =COUNTIFS(Triage!$C$2:$C$491,"*Q1*",Triage!$A$2:$A$491,"Relevant") | D10: =COUNTIFS(Triage!$C$2:$C$491,"*Q1*",Triage!$A$2:$A$491,"Maybe") | E10: =COUNTIFS(Triage!$C$2:$C$491,"*Q1*",Triage!$A$2:$A$491,"No") | F10: =B10-C10-D10-E10
A11: Q2 | B11: =COUNTIF(Triage!$C$2:$C$491,"*Q2*") | C11: =COUNTIFS(Triage!$C$2:$C$491,"*Q2*",Triage!$A$2:$A$491,"Relevant") | D11: =COUNTIFS(Triage!$C$2:$C$491,"*Q2*",Triage!$A$2:$A$491,"Maybe") | E11: =COUNTIFS(Triage!$C$2:$C$491,"*Q2*",Triage!$A$2:$A$491,"No") | F11: =B11-C11-D11-E11
A12: Q3 | B12: =COUNTIF(Triage!$C$2:$C$491,"*Q3*") | C12: =COUNTIFS(Triage!$C$2:$C$491,"*Q3*",Triage!$A$2:$A$491,"Relevant") | D12: =COUNTIFS(Triage!$C$2:$C$491,"*Q3*",Triage!$A$2:$A$491,"Maybe") | E12: =COUNTIFS(Triage!$C$2:$C$491,"*Q3*",Triage!$A$2:$A$491,"No") | F12: =B12-C12-D12-E12
A13: Q4 | B13: =COUNTIF(Triage!$C$2:$C$491,"*Q4*") | C13: =COUNTIFS(Triage!$C$2:$C$491,"*Q4*",Triage!$A$2:$A$491,"Relevant") | D13: =COUNTIFS(Triage!$C$2:$C$491,"*Q4*",Triage!$A$2:$A$491,"Maybe") | E13: =COUNTIFS(Triage!$C$2:$C$491,"*Q4*",Triage!$A$2:$A$491,"No") | F13: =B13-C13-D13-E13
A14: Q5 | B14: =COUNTIF(Triage!$C$2:$C$491,"*Q5*") | C14: =COUNTIFS(Triage!$C$2:$C$491,"*Q5*",Triage!$A$2:$A$491,"Relevant") | D14: =COUNTIFS(Triage!$C$2:$C$491,"*Q5*",Triage!$A$2:$A$491,"Maybe") | E14: =COUNTIFS(Triage!$C$2:$C$491,"*Q5*",Triage!$A$2:$A$491,"No") | F14: =B14-C14-D14-E14
A15: Unique cases | B15: =COUNTA(Triage!$E$2:$E$491)
A16: Q-rows count a case once per question it appears in, so they can sum to more than Unique cases.
